metno_locationforecast/__init__.py
metno_locationforecast/config.py
metno_locationforecast/data_containers.py
metno_locationforecast/forecast.py
metno_locationforecast/py.typed
metno_locationforecast-2.1.0.dist-info/LICENSE
metno_locationforecast-2.1.0.dist-info/METADATA
metno_locationforecast-2.1.0.dist-info/WHEEL
metno_locationforecast-2.1.0.dist-info/top_level.txt
metno_locationforecast-2.1.0.dist-info/RECORD
