Metadata-Version: 2.1
Name: metno-locationforecast
Version: 2.1.0
Summary: A Python interface for MET Norway's Locationforecast 2.0 service.
Author-email: Rory Sullivan <codingrory@gmail.com>
License: MIT License
Project-URL: Homepage, https://github.com/Rory-Sullivan/metno-locationforecast
Project-URL: Source, https://github.com/Rory-Sullivan/metno-locationforecast
Project-URL: Issues, https://github.com/Rory-Sullivan/metno-locationforecast/issues
Keywords: met,metno,norway,yr,locationforecast,location,forecast,weather,api,python,python3
Classifier: Development Status :: 5 - Production/Stable
Classifier: Intended Audience :: Developers
Classifier: Topic :: Software Development
Classifier: Topic :: Software Development :: Libraries
Classifier: License :: OSI Approved :: MIT License
Classifier: Programming Language :: Python :: 3
Classifier: Programming Language :: Python :: 3.9
Classifier: Programming Language :: Python :: 3.10
Classifier: Programming Language :: Python :: 3.11
Classifier: Programming Language :: Python :: 3.12
Classifier: Programming Language :: Python :: 3.13
Classifier: Programming Language :: Python :: 3 :: Only
Classifier: License :: OSI Approved :: MIT License
Requires-Python: >=3.9
License-File: LICENSE
Requires-Dist: requests>=2.25.1
Requires-Dist: tzdata>=2020.5
